fintrace/__init__.py
fintrace/drawing.py
fintrace/dxf2img.py
fintrace/fintrace_plot_yaml.py
fintrace/model.py
fintrace/utils.py
fintrace-1.0.0a2.dist-info/METADATA
fintrace-1.0.0a2.dist-info/WHEEL
fintrace-1.0.0a2.dist-info/entry_points.txt
fintrace-1.0.0a2.dist-info/top_level.txt
fintrace-1.0.0a2.dist-info/RECORD
