Metadata-Version: 2.4
Name: fintrace
Version: 1.0.0a2
Summary: An interferometer modeling and ray tracing program
Author-email: Matthew Todd <mactodd315@gmail.com>
Project-URL: Homepage, https://gitlab.com/mactodd315/fintrace
Project-URL: Issues, https://gitlab.com/mactodd315/fintrace/-/issues
Keywords: optics,ifo-modeling,ray-tracing
Classifier: Development Status :: 3 - Alpha
Classifier: Intended Audience :: Science/Research
Classifier: Topic :: Scientific/Engineering :: Physics
Classifier: Programming Language :: Python :: 3
Classifier: Operating System :: OS Independent
Requires-Python: >=3.8
Requires-Dist: finesse
Requires-Dist: gtrace
Requires-Dist: prettytable
Requires-Dist: termcolor
Requires-Dist: ezdxf
